{
    "wzElement": "svg",
    "wzName": "",
    "width": "800",
    "height": "450",
    "viewBox": "0 0 21.813 23.453",
    "comments": [],
    "attributes": [],
    "elements": [
        {
            "wzElement": "line",
            "wzTag": "line",
            "wzName": "",
            "dataName": "alfio",
            "stroke": "black",
            "x1": "20",
            "y1": "20",
            "x2": "120",
            "y2": "20",
            "comments": [],
            "attributes": [],
            "elements": []
        },
        {
            "wzElement": "rect",
            "wzTag": "rect",
            "wzName": "",
            "fill": "yellow",
            "stroke": "blue",
            "x": "20",
            "y": "30",
            "width": "100",
            "height": "50",
            "comments": [],
            "attributes": [],
            "elements": [
                {
                    "wzElement": "jsInclude",
                    "wzTag": "::script",
                    "wzName": "",
                    "comments": [],
                    "attributes": [],
                    "elements": []
                }
            ]
        },
        {
            "wzElement": "circle",
            "wzTag": "circle",
            "wzName": "",
            "fill": "green",
            "stroke": "red",
            "cx": "220",
            "cy": "70",
            "r": "50",
            "comments": [],
            "attributes": [],
            "elements": []
        },
        {
            "wzElement": "ellipse",
            "wzTag": "ellipse",
            "wzName": "",
            "fill": "green",
            "stroke": "red",
            "cx": "220",
            "cy": "170",
            "rx": "50",
            "ry": "30",
            "comments": [],
            "attributes": [],
            "elements": []
        },
        {
            "wzElement": "text",
            "wzTag": "text",
            "wzName": "Hello. Let's show:",
            "fill": "#000099",
            "stroke": "#000099",
            "fontSize": "18",
            "x": "10",
            "y": "220",
            "comments": [],
            "attributes": [],
            "elements": [
                {
                    "wzElement": "tspan",
                    "wzTag": "tspan",
                    "wzName": "a blue rectangle that pops up and goes again",
                    "x": "55",
                    "dy": "20",
                    "comments": [],
                    "attributes": [],
                    "elements": []
                },
                {
                    "wzElement": "tspan",
                    "wzTag": "tspan",
                    "wzName": "and a yellow that slowly arrives and then stays!",
                    "x": "55",
                    "dy": "40",
                    "comments": [],
                    "attributes": [],
                    "elements": []
                }
            ]
        },
        {
            "wzElement": "defs",
            "wzTag": "defs",
            "wzName": "",
            "comments": [],
            "attributes": [],
            "elements": [
                {
                    "wzElement": "linearGradient",
                    "wzTag": "linearGradient",
                    "wzName": "",
                    "id": "Gradient1",
                    "comments": [],
                    "attributes": [],
                    "elements": [
                        {
                            "wzElement": "stop",
                            "wzTag": "stop",
                            "wzName": "",
                            "class": "stop1",
                            "offset": "0%",
                            "comments": [],
                            "attributes": [],
                            "elements": []
                        },
                        {
                            "wzElement": "stop",
                            "wzTag": "stop",
                            "wzName": "",
                            "class": "stop2",
                            "offset": "50%",
                            "comments": [],
                            "attributes": [],
                            "elements": []
                        },
                        {
                            "wzElement": "stop",
                            "wzTag": "stop",
                            "wzName": "",
                            "class": "stop3",
                            "offset": "100%",
                            "comments": [],
                            "attributes": [],
                            "elements": []
                        }
                    ]
                }
            ]
        },
        {
            "wzElement": "rect",
            "wzTag": "rect",
            "wzName": "",
            "fill": "red",
            "width": "100%",
            "height": "100%",
            "comments": [],
            "attributes": [],
            "elements": []
        },
        {
            "wzElement": "circle",
            "wzTag": "circle",
            "wzName": "",
            "fill": "green",
            "cx": "150",
            "cy": "100",
            "r": "80",
            "comments": [],
            "attributes": [],
            "elements": []
        },
        {
            "wzElement": "text",
            "wzTag": "text",
            "wzName": "SVG",
            "fill": "white",
            "fontSize": "60",
            "textAnchor": "middle",
            "x": "150",
            "y": "125",
            "comments": [],
            "attributes": [],
            "elements": []
        }
    ]
}