{"pandoc-api-version":[1,23],"meta":{"ICBM":{"t":"MetaInlines","c":[{"t":"Str","c":"42.355469,-71.058627"}]},"lang":{"t":"MetaInlines","c":[{"t":"Str","c":"en"}]},"title":{"t":"MetaInlines","c":[{"t":"Str","c":"Make"},{"t":"SoftBreak"},{"t":"Str","c":"-"},{"t":"Space"},{"t":"Str","c":"GNU"},{"t":"Space"},{"t":"Str","c":"Project"},{"t":"Space"},{"t":"Str","c":"-"},{"t":"Space"},{"t":"Str","c":"Free"},{"t":"Space"},{"t":"Str","c":"Software"},{"t":"Space"},{"t":"Str","c":"Foundation"}]},"viewport":{"t":"MetaInlines","c":[{"t":"Str","c":"width=device-width,"},{"t":"Space"},{"t":"Str","c":"initial-scale=1"}]}},"blocks":[{"t":"Div","c":[["",["inner"],[]],[{"t":"Div","c":[["top",[],[]],[{"t":"Plain","c":[{"t":"Link","c":[["",["skip"],[]],[{"t":"Strong","c":[{"t":"Str","c":"Skip"},{"t":"Space"},{"t":"Str","c":"to"},{"t":"Space"},{"t":"Str","c":"main"},{"t":"Space"},{"t":"Str","c":"text"}]}],["#content",""]]}]}]]},{"t":"Div","c":[["fsf-frame",[],[["role","complementary"]]],[{"t":"Div","c":[["",[],[]],[{"t":"Plain","c":[{"t":"Link","c":[["",[],[]],[{"t":"Str","c":"Free"},{"t":"Space"},{"t":"Str","c":"Software"},{"t":"Space"},{"t":"Str","c":"Supporter"}],["//www.fsf.org/fss",""]]},{"t":"Str","c":":"}]}]]},{"t":"Div","c":[["join-fsf",["button"],[]],[{"t":"Plain","c":[{"t":"Link","c":[["",[],[]],[{"t":"Str","c":"JOIN THE FSF"}],["https://www.fsf.org/associate/support_freedom?referrer=4052",""]]}]}]]}]]},{"t":"Div","c":[["header",[],[["role","banner"]]],[{"t":"Para","c":[{"t":"Link","c":[["",[],[]],[{"t":"Image","c":[["",[],[["height","48"],["width","49"]]],[{"t":"Str","c":" [A"},{"t":"Space"},{"t":"Str","c":"GNU"},{"t":"Space"},{"t":"Str","c":"head] "}],["/graphics/heckert_gnu.transp.small.png",""]]},{"t":"Strong","c":[{"t":"Str","c":"GNU"}]},{"t":"Space"},{"t":"Span","c":[["",["hide"],[]],[{"t":"Str","c":"Operating"},{"t":"Space"},{"t":"Str","c":"System"}]]}],["/",""]]},{"t":"LineBreak"},{"t":"Span","c":[["",["small"],[]],[{"t":"Str","c":"Supported"},{"t":"Space"},{"t":"Str","c":"by"},{"t":"Space"},{"t":"Str","c":"the"},{"t":"SoftBreak"},{"t":"Link","c":[["",[],[]],[{"t":"Str","c":"Free"},{"t":"Space"},{"t":"Str","c":"Software"},{"t":"Space"},{"t":"Str","c":"Foundation"}],["#mission-statement",""]]}]]}]},{"t":"Div","c":[["switches",[],[]],[{"t":"Div","c":[["search-button",["switch"],[]],[{"t":"Plain","c":[{"t":"Link","c":[["",[],[]],[{"t":"Image","c":[["search-icon",[],[["height","30"],["width","30"]]],[{"t":"Str","c":" [Search"},{"t":"Space"},{"t":"Str","c":"www.gnu.org] "}],["/graphics/icons/search.png","Site search"]]}],["//www.gnu.org/cgi-bin/estseek.cgi",""]]}]}]]}]]}]]},{"t":"Div","c":[["",[],[["style","clear: both"]]],[]]},{"t":"Div","c":[["navigation",[],[["role","navigation"]]],[{"t":"Plain","c":[{"t":"Link","c":[["more-links",[],[]],[{"t":"Span","c":[["",[],[]],[{"t":"Str","c":"Site"},{"t":"Space"},{"t":"Str","c":"navigation"}]]}],["#navigation","More..."]]},{"t":"SoftBreak"},{"t":"Link","c":[["less-links",[],[]],[{"t":"Strong","c":[{"t":"Str","c":"Skip"}]}],["#content",""]]}]},{"t":"BulletList","c":[[{"t":"Plain","c":[{"t":"Span","c":[["tabAboutGNU",[],[]],[{"t":"Link","c":[["",[],[]],[{"t":"Str","c":"ABOUT GNU"}],["/gnu/gnu.html",""]]}]]}]}],[{"t":"Plain","c":[{"t":"Span","c":[["tabPhilosophy",[],[]],[{"t":"Link","c":[["",[],[]],[{"t":"Str","c":"PHILOSOPHY"}],["/philosophy/philosophy.html",""]]}]]}]}],[{"t":"Plain","c":[{"t":"Span","c":[["tabLicenses",[],[]],[{"t":"Link","c":[["",[],[]],[{"t":"Str","c":"LICENSES"}],["/licenses/licenses.html",""]]}]]}]}],[{"t":"Plain","c":[{"t":"Span","c":[["tabEducation",[],[]],[{"t":"Link","c":[["",[],[]],[{"t":"Str","c":"EDUCATION"}],["/education/education.html",""]]}]]}]}],[{"t":"Plain","c":[{"t":"Span","c":[["tabSoftware",[],[]],[{"t":"Span","c":[["",["no-display"],[]],[{"t":"Str","c":"="}]]},{"t":"SoftBreak"},{"t":"Link","c":[["",[],[]],[{"t":"Str","c":"SOFTWARE"}],["/software/software.html",""]]},{"t":"SoftBreak"},{"t":"Span","c":[["",["gnun-split"],[]],[]]},{"t":"SoftBreak"},{"t":"Span","c":[["",["no-display"],[]],[{"t":"Str","c":"="}]]}]]}]}],[{"t":"Plain","c":[{"t":"Span","c":[["tabDistros",[],[]],[{"t":"Link","c":[["",[],[]],[{"t":"Str","c":"DISTROS"}],["/distros/distros.html",""]]}]]}]}],[{"t":"Plain","c":[{"t":"Span","c":[["tabDoc",[],[]],[{"t":"Link","c":[["",[],[]],[{"t":"Str","c":"DOCS"}],["/doc/doc.html",""]]}]]}]}],[{"t":"Plain","c":[{"t":"Span","c":[["tabMalware",[],[]],[{"t":"Link","c":[["",[],[]],[{"t":"Str","c":"MALWARE"}],["/proprietary/proprietary.html",""]]}]]}]}],[{"t":"Plain","c":[{"t":"Span","c":[["tabHelp",[],[]],[{"t":"Link","c":[["",[],[]],[{"t":"Str","c":"HELP GNU"}],["/help/help.html",""]]}]]}]}],[{"t":"Plain","c":[{"t":"Span","c":[["tabAV",[],[]],[{"t":"Link","c":[["",[],[]],[{"t":"Str","c":"AUDIO & VIDEO"}],["/audio-video/audio-video.html",""]]}]]}]}],[{"t":"Plain","c":[{"t":"Span","c":[["tabArt",[],[]],[{"t":"Link","c":[["",[],[]],[{"t":"Str","c":"GNU ART"}],["/graphics/graphics.html",""]]}]]}]}],[{"t":"Plain","c":[{"t":"Span","c":[["tabFun",[],[]],[{"t":"Link","c":[["",[],[]],[{"t":"Str","c":"FUN"}],["/fun/humor.html",""]]}]]}]}],[{"t":"Plain","c":[{"t":"Span","c":[["tabPeople",[],[]],[{"t":"Link","c":[["",[],[]],[{"t":"Str","c":"GNU'S WHO?"}],["/people/people.html",""]]}]]}]}],[{"t":"Plain","c":[{"t":"Link","c":[["",[],[]],[{"t":"Str","c":"SOFTWARE DIRECTORY"}],["//directory.fsf.org",""]]}]}],[{"t":"Plain","c":[{"t":"Link","c":[["",[],[]],[{"t":"Str","c":"HARDWARE"}],["https://h-node.org/",""]]}]}],[{"t":"Plain","c":[{"t":"Link","c":[["",[],[]],[{"t":"Str","c":"SITEMAP"}],["/server/sitemap.html",""]]}]}]]},{"t":"Div","c":[["",[],[["style","clear: both"]]],[]]}]]},{"t":"Div","c":[["content",[],[["role","main"]]],[{"t":"Header","c":[2,["gnu-make",[],[]],[{"t":"Str","c":"GNU"},{"t":"Space"},{"t":"Str","c":"Make"}]]},{"t":"Para","c":[{"t":"Str","c":"GNU"},{"t":"Space"},{"t":"Str","c":"Make"},{"t":"Space"},{"t":"Str","c":"is"},{"t":"Space"},{"t":"Str","c":"a"},{"t":"Space"},{"t":"Str","c":"tool"},{"t":"Space"},{"t":"Str","c":"which"},{"t":"Space"},{"t":"Str","c":"controls"},{"t":"Space"},{"t":"Str","c":"the"},{"t":"Space"},{"t":"Str","c":"generation"},{"t":"Space"},{"t":"Str","c":"of"},{"t":"Space"},{"t":"Str","c":"executables"},{"t":"Space"},{"t":"Str","c":"and"},{"t":"Space"},{"t":"Str","c":"other"},{"t":"SoftBreak"},{"t":"Str","c":"non-source"},{"t":"Space"},{"t":"Str","c":"files"},{"t":"Space"},{"t":"Str","c":"of"},{"t":"Space"},{"t":"Str","c":"a"},{"t":"Space"},{"t":"Str","c":"program"},{"t":"Space"},{"t":"Str","c":"from"},{"t":"Space"},{"t":"Str","c":"the"},{"t":"Space"},{"t":"Str","c":"program's"},{"t":"Space"},{"t":"Str","c":"source"},{"t":"Space"},{"t":"Str","c":"files."}]},{"t":"Para","c":[{"t":"Str","c":"Make"},{"t":"Space"},{"t":"Str","c":"gets"},{"t":"Space"},{"t":"Str","c":"its"},{"t":"Space"},{"t":"Str","c":"knowledge"},{"t":"Space"},{"t":"Str","c":"of"},{"t":"Space"},{"t":"Str","c":"how"},{"t":"Space"},{"t":"Str","c":"to"},{"t":"Space"},{"t":"Str","c":"build"},{"t":"Space"},{"t":"Str","c":"your"},{"t":"Space"},{"t":"Str","c":"program"},{"t":"Space"},{"t":"Str","c":"from"},{"t":"Space"},{"t":"Str","c":"a"},{"t":"Space"},{"t":"Str","c":"file"},{"t":"SoftBreak"},{"t":"Str","c":"called"},{"t":"Space"},{"t":"Str","c":"the"},{"t":"Space"},{"t":"Emph","c":[{"t":"Str","c":"makefile"}]},{"t":"Str","c":","},{"t":"Space"},{"t":"Str","c":"which"},{"t":"Space"},{"t":"Str","c":"lists"},{"t":"Space"},{"t":"Str","c":"each"},{"t":"Space"},{"t":"Str","c":"of"},{"t":"Space"},{"t":"Str","c":"the"},{"t":"Space"},{"t":"Str","c":"non-source"},{"t":"Space"},{"t":"Str","c":"files"},{"t":"SoftBreak"},{"t":"Str","c":"and"},{"t":"Space"},{"t":"Str","c":"how"},{"t":"Space"},{"t":"Str","c":"to"},{"t":"Space"},{"t":"Str","c":"compute"},{"t":"Space"},{"t":"Str","c":"it"},{"t":"Space"},{"t":"Str","c":"from"},{"t":"Space"},{"t":"Str","c":"other"},{"t":"Space"},{"t":"Str","c":"files."},{"t":"Space"},{"t":"Str","c":"When"},{"t":"Space"},{"t":"Str","c":"you"},{"t":"Space"},{"t":"Str","c":"write"},{"t":"Space"},{"t":"Str","c":"a"},{"t":"Space"},{"t":"Str","c":"program,"},{"t":"Space"},{"t":"Str","c":"you"},{"t":"SoftBreak"},{"t":"Str","c":"should"},{"t":"Space"},{"t":"Str","c":"write"},{"t":"Space"},{"t":"Str","c":"a"},{"t":"Space"},{"t":"Str","c":"makefile"},{"t":"Space"},{"t":"Str","c":"for"},{"t":"Space"},{"t":"Str","c":"it,"},{"t":"Space"},{"t":"Str","c":"so"},{"t":"Space"},{"t":"Str","c":"that"},{"t":"Space"},{"t":"Str","c":"it"},{"t":"Space"},{"t":"Str","c":"is"},{"t":"Space"},{"t":"Str","c":"possible"},{"t":"Space"},{"t":"Str","c":"to"},{"t":"Space"},{"t":"Str","c":"use"},{"t":"Space"},{"t":"Str","c":"Make"},{"t":"Space"},{"t":"Str","c":"to"},{"t":"SoftBreak"},{"t":"Str","c":"build"},{"t":"Space"},{"t":"Str","c":"and"},{"t":"Space"},{"t":"Str","c":"install"},{"t":"Space"},{"t":"Str","c":"the"},{"t":"Space"},{"t":"Str","c":"program."}]},{"t":"Header","c":[4,["capabilities-of-make",[],[]],[{"t":"Str","c":"Capabilities"},{"t":"Space"},{"t":"Str","c":"of"},{"t":"Space"},{"t":"Str","c":"Make"}]]},{"t":"BulletList","c":[[{"t":"Plain","c":[{"t":"Str","c":"Make"},{"t":"Space"},{"t":"Str","c":"enables"},{"t":"Space"},{"t":"Str","c":"the"},{"t":"Space"},{"t":"Str","c":"end"},{"t":"Space"},{"t":"Str","c":"user"},{"t":"Space"},{"t":"Str","c":"to"},{"t":"Space"},{"t":"Str","c":"build"},{"t":"Space"},{"t":"Str","c":"and"},{"t":"Space"},{"t":"Str","c":"install"},{"t":"Space"},{"t":"Str","c":"your"},{"t":"Space"},{"t":"Str","c":"package"},{"t":"SoftBreak"},{"t":"Str","c":"without"},{"t":"Space"},{"t":"Str","c":"knowing"},{"t":"Space"},{"t":"Str","c":"the"},{"t":"Space"},{"t":"Str","c":"details"},{"t":"Space"},{"t":"Str","c":"of"},{"t":"Space"},{"t":"Str","c":"how"},{"t":"Space"},{"t":"Str","c":"that"},{"t":"Space"},{"t":"Str","c":"is"},{"t":"Space"},{"t":"Str","c":"done"},{"t":"Space"},{"t":"Str","c":"--"},{"t":"Space"},{"t":"Str","c":"because"},{"t":"Space"},{"t":"Str","c":"these"},{"t":"SoftBreak"},{"t":"Str","c":"details"},{"t":"Space"},{"t":"Str","c":"are"},{"t":"Space"},{"t":"Str","c":"recorded"},{"t":"Space"},{"t":"Str","c":"in"},{"t":"Space"},{"t":"Str","c":"the"},{"t":"Space"},{"t":"Str","c":"makefile"},{"t":"Space"},{"t":"Str","c":"that"},{"t":"Space"},{"t":"Str","c":"you"},{"t":"Space"},{"t":"Str","c":"supply."}]}],[{"t":"Para","c":[{"t":"Str","c":"Make"},{"t":"Space"},{"t":"Str","c":"figures"},{"t":"Space"},{"t":"Str","c":"out"},{"t":"Space"},{"t":"Str","c":"automatically"},{"t":"Space"},{"t":"Str","c":"which"},{"t":"Space"},{"t":"Str","c":"files"},{"t":"Space"},{"t":"Str","c":"it"},{"t":"Space"},{"t":"Str","c":"needs"},{"t":"Space"},{"t":"Str","c":"to"},{"t":"Space"},{"t":"Str","c":"update,"},{"t":"SoftBreak"},{"t":"Str","c":"based"},{"t":"Space"},{"t":"Str","c":"on"},{"t":"Space"},{"t":"Str","c":"which"},{"t":"Space"},{"t":"Str","c":"source"},{"t":"Space"},{"t":"Str","c":"files"},{"t":"Space"},{"t":"Str","c":"have"},{"t":"Space"},{"t":"Str","c":"changed."},{"t":"Space"},{"t":"Str","c":"It"},{"t":"Space"},{"t":"Str","c":"also"},{"t":"Space"},{"t":"Str","c":"automatically"},{"t":"SoftBreak"},{"t":"Str","c":"determines"},{"t":"Space"},{"t":"Str","c":"the"},{"t":"Space"},{"t":"Str","c":"proper"},{"t":"Space"},{"t":"Str","c":"order"},{"t":"Space"},{"t":"Str","c":"for"},{"t":"Space"},{"t":"Str","c":"updating"},{"t":"Space"},{"t":"Str","c":"files,"},{"t":"Space"},{"t":"Str","c":"in"},{"t":"Space"},{"t":"Str","c":"case"},{"t":"Space"},{"t":"Str","c":"one"},{"t":"Space"},{"t":"Str","c":"non-source"},{"t":"SoftBreak"},{"t":"Str","c":"file"},{"t":"Space"},{"t":"Str","c":"depends"},{"t":"Space"},{"t":"Str","c":"on"},{"t":"Space"},{"t":"Str","c":"another"},{"t":"Space"},{"t":"Str","c":"non-source"},{"t":"Space"},{"t":"Str","c":"file."}]},{"t":"Para","c":[{"t":"Str","c":"As"},{"t":"Space"},{"t":"Str","c":"a"},{"t":"Space"},{"t":"Str","c":"result,"},{"t":"Space"},{"t":"Str","c":"if"},{"t":"Space"},{"t":"Str","c":"you"},{"t":"Space"},{"t":"Str","c":"change"},{"t":"Space"},{"t":"Str","c":"a"},{"t":"Space"},{"t":"Str","c":"few"},{"t":"Space"},{"t":"Str","c":"source"},{"t":"Space"},{"t":"Str","c":"files"},{"t":"Space"},{"t":"Str","c":"and"},{"t":"Space"},{"t":"Str","c":"then"},{"t":"Space"},{"t":"Str","c":"run"},{"t":"Space"},{"t":"Str","c":"Make,"},{"t":"Space"},{"t":"Str","c":"it"},{"t":"SoftBreak"},{"t":"Str","c":"does"},{"t":"Space"},{"t":"Str","c":"not"},{"t":"Space"},{"t":"Str","c":"need"},{"t":"Space"},{"t":"Str","c":"to"},{"t":"Space"},{"t":"Str","c":"recompile"},{"t":"Space"},{"t":"Str","c":"all"},{"t":"Space"},{"t":"Str","c":"of"},{"t":"Space"},{"t":"Str","c":"your"},{"t":"Space"},{"t":"Str","c":"program."},{"t":"Space"},{"t":"Str","c":"It"},{"t":"Space"},{"t":"Str","c":"updates"},{"t":"Space"},{"t":"Str","c":"only"},{"t":"Space"},{"t":"Str","c":"those"},{"t":"SoftBreak"},{"t":"Str","c":"non-source"},{"t":"Space"},{"t":"Str","c":"files"},{"t":"Space"},{"t":"Str","c":"that"},{"t":"Space"},{"t":"Str","c":"depend"},{"t":"Space"},{"t":"Str","c":"directly"},{"t":"Space"},{"t":"Str","c":"or"},{"t":"Space"},{"t":"Str","c":"indirectly"},{"t":"Space"},{"t":"Str","c":"on"},{"t":"Space"},{"t":"Str","c":"the"},{"t":"Space"},{"t":"Str","c":"source"},{"t":"SoftBreak"},{"t":"Str","c":"files"},{"t":"Space"},{"t":"Str","c":"that"},{"t":"Space"},{"t":"Str","c":"you"},{"t":"Space"},{"t":"Str","c":"changed."}]}],[{"t":"Plain","c":[{"t":"Str","c":"Make"},{"t":"Space"},{"t":"Str","c":"is"},{"t":"Space"},{"t":"Str","c":"not"},{"t":"Space"},{"t":"Str","c":"limited"},{"t":"Space"},{"t":"Str","c":"to"},{"t":"Space"},{"t":"Str","c":"any"},{"t":"Space"},{"t":"Str","c":"particular"},{"t":"Space"},{"t":"Str","c":"language."},{"t":"Space"},{"t":"Str","c":"For"},{"t":"Space"},{"t":"Str","c":"each"},{"t":"SoftBreak"},{"t":"Str","c":"non-source"},{"t":"Space"},{"t":"Str","c":"file"},{"t":"Space"},{"t":"Str","c":"in"},{"t":"Space"},{"t":"Str","c":"the"},{"t":"Space"},{"t":"Str","c":"program,"},{"t":"Space"},{"t":"Str","c":"the"},{"t":"Space"},{"t":"Str","c":"makefile"},{"t":"Space"},{"t":"Str","c":"specifies"},{"t":"Space"},{"t":"Str","c":"the"},{"t":"Space"},{"t":"Str","c":"shell"},{"t":"SoftBreak"},{"t":"Str","c":"commands"},{"t":"Space"},{"t":"Str","c":"to"},{"t":"Space"},{"t":"Str","c":"compute"},{"t":"Space"},{"t":"Str","c":"it."},{"t":"Space"},{"t":"Str","c":"These"},{"t":"Space"},{"t":"Str","c":"shell"},{"t":"Space"},{"t":"Str","c":"commands"},{"t":"Space"},{"t":"Str","c":"can"},{"t":"Space"},{"t":"Str","c":"run"},{"t":"Space"},{"t":"Str","c":"a"},{"t":"Space"},{"t":"Str","c":"compiler"},{"t":"Space"},{"t":"Str","c":"to"},{"t":"SoftBreak"},{"t":"Str","c":"produce"},{"t":"Space"},{"t":"Str","c":"an"},{"t":"Space"},{"t":"Str","c":"object"},{"t":"Space"},{"t":"Str","c":"file,"},{"t":"Space"},{"t":"Str","c":"the"},{"t":"Space"},{"t":"Str","c":"linker"},{"t":"Space"},{"t":"Str","c":"to"},{"t":"Space"},{"t":"Str","c":"produce"},{"t":"Space"},{"t":"Str","c":"an"},{"t":"Space"},{"t":"Str","c":"executable,"},{"t":"SoftBreak"},{"t":"Code","c":[["",[],[]],"ar"]},{"t":"Space"},{"t":"Str","c":"to"},{"t":"Space"},{"t":"Str","c":"update"},{"t":"Space"},{"t":"Str","c":"a"},{"t":"Space"},{"t":"Str","c":"library,"},{"t":"Space"},{"t":"Str","c":"or"},{"t":"Space"},{"t":"Str","c":"TeX"},{"t":"Space"},{"t":"Str","c":"or"},{"t":"Space"},{"t":"Str","c":"Makeinfo"},{"t":"Space"},{"t":"Str","c":"to"},{"t":"Space"},{"t":"Str","c":"format"},{"t":"SoftBreak"},{"t":"Str","c":"documentation."}]}],[{"t":"Plain","c":[{"t":"Str","c":"Make"},{"t":"Space"},{"t":"Str","c":"is"},{"t":"Space"},{"t":"Str","c":"not"},{"t":"Space"},{"t":"Str","c":"limited"},{"t":"Space"},{"t":"Str","c":"to"},{"t":"Space"},{"t":"Str","c":"building"},{"t":"Space"},{"t":"Str","c":"a"},{"t":"Space"},{"t":"Str","c":"package."},{"t":"Space"},{"t":"Str","c":"You"},{"t":"Space"},{"t":"Str","c":"can"},{"t":"Space"},{"t":"Str","c":"also"},{"t":"Space"},{"t":"Str","c":"use"},{"t":"Space"},{"t":"Str","c":"Make"},{"t":"SoftBreak"},{"t":"Str","c":"to"},{"t":"Space"},{"t":"Str","c":"control"},{"t":"Space"},{"t":"Str","c":"installing"},{"t":"Space"},{"t":"Str","c":"or"},{"t":"Space"},{"t":"Str","c":"deinstalling"},{"t":"Space"},{"t":"Str","c":"a"},{"t":"Space"},{"t":"Str","c":"package,"},{"t":"Space"},{"t":"Str","c":"generate"},{"t":"Space"},{"t":"Str","c":"tags"},{"t":"Space"},{"t":"Str","c":"tables"},{"t":"Space"},{"t":"Str","c":"for"},{"t":"SoftBreak"},{"t":"Str","c":"it,"},{"t":"Space"},{"t":"Str","c":"or"},{"t":"Space"},{"t":"Str","c":"anything"},{"t":"Space"},{"t":"Str","c":"else"},{"t":"Space"},{"t":"Str","c":"you"},{"t":"Space"},{"t":"Str","c":"want"},{"t":"Space"},{"t":"Str","c":"to"},{"t":"Space"},{"t":"Str","c":"do"},{"t":"Space"},{"t":"Str","c":"often"},{"t":"Space"},{"t":"Str","c":"enough"},{"t":"Space"},{"t":"Str","c":"to"},{"t":"Space"},{"t":"Str","c":"make"},{"t":"Space"},{"t":"Str","c":"it"},{"t":"Space"},{"t":"Str","c":"worth"},{"t":"SoftBreak"},{"t":"Str","c":"while"},{"t":"Space"},{"t":"Str","c":"writing"},{"t":"Space"},{"t":"Str","c":"down"},{"t":"Space"},{"t":"Str","c":"how"},{"t":"Space"},{"t":"Str","c":"to"},{"t":"Space"},{"t":"Str","c":"do"},{"t":"Space"},{"t":"Str","c":"it."}]}]]},{"t":"Div","c":[["",["summary"],[]],[{"t":"HorizontalRule"},{"t":"Header","c":[3,["table-of-contents",["no-display"],[]],[{"t":"Str","c":"Table"},{"t":"Space"},{"t":"Str","c":"of"},{"t":"Space"},{"t":"Str","c":"contents"}]]},{"t":"BulletList","c":[[{"t":"Plain","c":[{"t":"Link","c":[["",[],[]],[{"t":"Str","c":"Download"}],["#download",""]]}]}],[{"t":"Plain","c":[{"t":"Link","c":[["",[],[]],[{"t":"Str","c":"Documentation"}],["#documentation",""]]}]}],[{"t":"Plain","c":[{"t":"Link","c":[["",[],[]],[{"t":"Str","c":"Mailing"},{"t":"Space"},{"t":"Str","c":"lists"}],["#mail",""]]}]}],[{"t":"Plain","c":[{"t":"Link","c":[["",[],[]],[{"t":"Str","c":"Getting"},{"t":"Space"},{"t":"Str","c":"involved"}],["#contribute",""]]}]}],[{"t":"Plain","c":[{"t":"Link","c":[["",[],[]],[{"t":"Str","c":"Licensing"}],["#license",""]]}]}]]},{"t":"HorizontalRule"}]]},{"t":"Header","c":[4,["make-rules-and-targets",[],[]],[{"t":"Str","c":"Make"},{"t":"Space"},{"t":"Str","c":"Rules"},{"t":"Space"},{"t":"Str","c":"and"},{"t":"Space"},{"t":"Str","c":"Targets"}]]},{"t":"Para","c":[{"t":"Str","c":"A"},{"t":"Space"},{"t":"Emph","c":[{"t":"Str","c":"rule"}]},{"t":"Space"},{"t":"Str","c":"in"},{"t":"Space"},{"t":"Str","c":"the"},{"t":"Space"},{"t":"Str","c":"makefile"},{"t":"Space"},{"t":"Str","c":"tells"},{"t":"Space"},{"t":"Str","c":"Make"},{"t":"Space"},{"t":"Str","c":"how"},{"t":"Space"},{"t":"Str","c":"to"},{"t":"Space"},{"t":"Str","c":"execute"},{"t":"Space"},{"t":"Str","c":"a"},{"t":"Space"},{"t":"Str","c":"series"},{"t":"Space"},{"t":"Str","c":"of"},{"t":"SoftBreak"},{"t":"Str","c":"commands"},{"t":"Space"},{"t":"Str","c":"in"},{"t":"Space"},{"t":"Str","c":"order"},{"t":"Space"},{"t":"Str","c":"to"},{"t":"Space"},{"t":"Str","c":"build"},{"t":"Space"},{"t":"Str","c":"a"},{"t":"Space"},{"t":"Emph","c":[{"t":"Str","c":"target"}]},{"t":"Space"},{"t":"Str","c":"file"},{"t":"Space"},{"t":"Str","c":"from"},{"t":"Space"},{"t":"Str","c":"source"},{"t":"Space"},{"t":"Str","c":"files."},{"t":"SoftBreak"},{"t":"Str","c":"It"},{"t":"Space"},{"t":"Str","c":"also"},{"t":"Space"},{"t":"Str","c":"specifies"},{"t":"Space"},{"t":"Str","c":"a"},{"t":"Space"},{"t":"Str","c":"list"},{"t":"Space"},{"t":"Str","c":"of"},{"t":"Space"},{"t":"Emph","c":[{"t":"Str","c":"dependencies"}]},{"t":"Space"},{"t":"Str","c":"of"},{"t":"Space"},{"t":"Str","c":"the"},{"t":"Space"},{"t":"Str","c":"target"},{"t":"Space"},{"t":"Str","c":"file."},{"t":"SoftBreak"},{"t":"Str","c":"This"},{"t":"Space"},{"t":"Str","c":"list"},{"t":"Space"},{"t":"Str","c":"should"},{"t":"Space"},{"t":"Str","c":"include"},{"t":"Space"},{"t":"Str","c":"all"},{"t":"Space"},{"t":"Str","c":"files"},{"t":"Space"},{"t":"Str","c":"(whether"},{"t":"Space"},{"t":"Str","c":"source"},{"t":"Space"},{"t":"Str","c":"files"},{"t":"Space"},{"t":"Str","c":"or"},{"t":"Space"},{"t":"Str","c":"other"},{"t":"Space"},{"t":"Str","c":"targets)"},{"t":"SoftBreak"},{"t":"Str","c":"which"},{"t":"Space"},{"t":"Str","c":"are"},{"t":"Space"},{"t":"Str","c":"used"},{"t":"Space"},{"t":"Str","c":"as"},{"t":"Space"},{"t":"Str","c":"inputs"},{"t":"Space"},{"t":"Str","c":"to"},{"t":"Space"},{"t":"Str","c":"the"},{"t":"Space"},{"t":"Str","c":"commands"},{"t":"Space"},{"t":"Str","c":"in"},{"t":"Space"},{"t":"Str","c":"the"},{"t":"Space"},{"t":"Str","c":"rule."}]},{"t":"Para","c":[{"t":"Str","c":"Here"},{"t":"Space"},{"t":"Str","c":"is"},{"t":"Space"},{"t":"Str","c":"what"},{"t":"Space"},{"t":"Str","c":"a"},{"t":"Space"},{"t":"Str","c":"simple"},{"t":"Space"},{"t":"Str","c":"rule"},{"t":"Space"},{"t":"Str","c":"looks"},{"t":"Space"},{"t":"Str","c":"like:"}]},{"t":"CodeBlock","c":[["",[],[]],"target:   dependencies ...\n          commands\n          ..."]},{"t":"Para","c":[{"t":"Str","c":"When"},{"t":"Space"},{"t":"Str","c":"you"},{"t":"Space"},{"t":"Str","c":"run"},{"t":"Space"},{"t":"Str","c":"Make,"},{"t":"Space"},{"t":"Str","c":"you"},{"t":"Space"},{"t":"Str","c":"can"},{"t":"Space"},{"t":"Str","c":"specify"},{"t":"Space"},{"t":"Str","c":"particular"},{"t":"Space"},{"t":"Str","c":"targets"},{"t":"Space"},{"t":"Str","c":"to"},{"t":"Space"},{"t":"Str","c":"update;"},{"t":"SoftBreak"},{"t":"Str","c":"otherwise,"},{"t":"Space"},{"t":"Str","c":"Make"},{"t":"Space"},{"t":"Str","c":"updates"},{"t":"Space"},{"t":"Str","c":"the"},{"t":"Space"},{"t":"Str","c":"first"},{"t":"Space"},{"t":"Str","c":"target"},{"t":"Space"},{"t":"Str","c":"listed"},{"t":"Space"},{"t":"Str","c":"in"},{"t":"Space"},{"t":"Str","c":"the"},{"t":"Space"},{"t":"Str","c":"makefile."},{"t":"Space"},{"t":"Str","c":"Of"},{"t":"SoftBreak"},{"t":"Str","c":"course,"},{"t":"Space"},{"t":"Str","c":"any"},{"t":"Space"},{"t":"Str","c":"other"},{"t":"Space"},{"t":"Str","c":"target"},{"t":"Space"},{"t":"Str","c":"files"},{"t":"Space"},{"t":"Str","c":"needed"},{"t":"Space"},{"t":"Str","c":"as"},{"t":"Space"},{"t":"Str","c":"input"},{"t":"Space"},{"t":"Str","c":"for"},{"t":"Space"},{"t":"Str","c":"generating"},{"t":"Space"},{"t":"Str","c":"these"},{"t":"SoftBreak"},{"t":"Str","c":"targets"},{"t":"Space"},{"t":"Str","c":"must"},{"t":"Space"},{"t":"Str","c":"be"},{"t":"Space"},{"t":"Str","c":"updated"},{"t":"Space"},{"t":"Str","c":"first."}]},{"t":"Para","c":[{"t":"Str","c":"Make"},{"t":"Space"},{"t":"Str","c":"uses"},{"t":"Space"},{"t":"Str","c":"the"},{"t":"Space"},{"t":"Str","c":"makefile"},{"t":"Space"},{"t":"Str","c":"to"},{"t":"Space"},{"t":"Str","c":"figure"},{"t":"Space"},{"t":"Str","c":"out"},{"t":"Space"},{"t":"Str","c":"which"},{"t":"Space"},{"t":"Str","c":"target"},{"t":"Space"},{"t":"Str","c":"files"},{"t":"Space"},{"t":"Str","c":"ought"},{"t":"Space"},{"t":"Str","c":"to"},{"t":"Space"},{"t":"Str","c":"be"},{"t":"SoftBreak"},{"t":"Str","c":"brought"},{"t":"Space"},{"t":"Str","c":"up"},{"t":"Space"},{"t":"Str","c":"to"},{"t":"Space"},{"t":"Str","c":"date,"},{"t":"Space"},{"t":"Str","c":"and"},{"t":"Space"},{"t":"Str","c":"then"},{"t":"Space"},{"t":"Str","c":"determines"},{"t":"Space"},{"t":"Str","c":"which"},{"t":"Space"},{"t":"Str","c":"of"},{"t":"Space"},{"t":"Str","c":"them"},{"t":"Space"},{"t":"Str","c":"actually"},{"t":"Space"},{"t":"Str","c":"need"},{"t":"Space"},{"t":"Str","c":"to"},{"t":"SoftBreak"},{"t":"Str","c":"be"},{"t":"Space"},{"t":"Str","c":"updated."},{"t":"Space"},{"t":"Str","c":"If"},{"t":"Space"},{"t":"Str","c":"a"},{"t":"Space"},{"t":"Str","c":"target"},{"t":"Space"},{"t":"Str","c":"file"},{"t":"Space"},{"t":"Str","c":"is"},{"t":"Space"},{"t":"Str","c":"newer"},{"t":"Space"},{"t":"Str","c":"than"},{"t":"Space"},{"t":"Str","c":"all"},{"t":"Space"},{"t":"Str","c":"of"},{"t":"Space"},{"t":"Str","c":"its"},{"t":"Space"},{"t":"Str","c":"dependencies,"},{"t":"SoftBreak"},{"t":"Str","c":"then"},{"t":"Space"},{"t":"Str","c":"it"},{"t":"Space"},{"t":"Str","c":"is"},{"t":"Space"},{"t":"Str","c":"already"},{"t":"Space"},{"t":"Str","c":"up"},{"t":"Space"},{"t":"Str","c":"to"},{"t":"Space"},{"t":"Str","c":"date,"},{"t":"Space"},{"t":"Str","c":"and"},{"t":"Space"},{"t":"Str","c":"it"},{"t":"Space"},{"t":"Str","c":"does"},{"t":"Space"},{"t":"Str","c":"not"},{"t":"Space"},{"t":"Str","c":"need"},{"t":"Space"},{"t":"Str","c":"to"},{"t":"Space"},{"t":"Str","c":"be"},{"t":"Space"},{"t":"Str","c":"regenerated."},{"t":"SoftBreak"},{"t":"Str","c":"The"},{"t":"Space"},{"t":"Str","c":"other"},{"t":"Space"},{"t":"Str","c":"target"},{"t":"Space"},{"t":"Str","c":"files"},{"t":"Space"},{"t":"Str","c":"do"},{"t":"Space"},{"t":"Str","c":"need"},{"t":"Space"},{"t":"Str","c":"to"},{"t":"Space"},{"t":"Str","c":"be"},{"t":"Space"},{"t":"Str","c":"updated,"},{"t":"Space"},{"t":"Str","c":"but"},{"t":"Space"},{"t":"Str","c":"in"},{"t":"Space"},{"t":"Str","c":"the"},{"t":"Space"},{"t":"Str","c":"right"},{"t":"Space"},{"t":"Str","c":"order:"},{"t":"SoftBreak"},{"t":"Str","c":"each"},{"t":"Space"},{"t":"Str","c":"target"},{"t":"Space"},{"t":"Str","c":"file"},{"t":"Space"},{"t":"Str","c":"must"},{"t":"Space"},{"t":"Str","c":"be"},{"t":"Space"},{"t":"Str","c":"regenerated"},{"t":"Space"},{"t":"Str","c":"before"},{"t":"Space"},{"t":"Str","c":"it"},{"t":"Space"},{"t":"Str","c":"is"},{"t":"Space"},{"t":"Str","c":"used"},{"t":"Space"},{"t":"Str","c":"in"},{"t":"Space"},{"t":"Str","c":"regenerating"},{"t":"SoftBreak"},{"t":"Str","c":"other"},{"t":"Space"},{"t":"Str","c":"targets."}]},{"t":"Header","c":[4,["advantages-of-gnu-make",[],[]],[{"t":"Str","c":"Advantages"},{"t":"Space"},{"t":"Str","c":"of"},{"t":"Space"},{"t":"Str","c":"GNU"},{"t":"Space"},{"t":"Str","c":"Make"}]]},{"t":"Para","c":[{"t":"Str","c":"GNU"},{"t":"Space"},{"t":"Str","c":"Make"},{"t":"Space"},{"t":"Str","c":"has"},{"t":"Space"},{"t":"Str","c":"many"},{"t":"Space"},{"t":"Str","c":"powerful"},{"t":"Space"},{"t":"Str","c":"features"},{"t":"Space"},{"t":"Str","c":"for"},{"t":"Space"},{"t":"Str","c":"use"},{"t":"Space"},{"t":"Str","c":"in"},{"t":"Space"},{"t":"Str","c":"makefiles,"},{"t":"Space"},{"t":"Str","c":"beyond"},{"t":"Space"},{"t":"Str","c":"what"},{"t":"SoftBreak"},{"t":"Str","c":"other"},{"t":"Space"},{"t":"Str","c":"Make"},{"t":"Space"},{"t":"Str","c":"versions"},{"t":"Space"},{"t":"Str","c":"have."},{"t":"Space"},{"t":"Str","c":"It"},{"t":"Space"},{"t":"Str","c":"can"},{"t":"Space"},{"t":"Str","c":"also"},{"t":"Space"},{"t":"Str","c":"regenerate,"},{"t":"Space"},{"t":"Str","c":"use,"},{"t":"Space"},{"t":"Str","c":"and"},{"t":"Space"},{"t":"Str","c":"then"},{"t":"Space"},{"t":"Str","c":"delete"},{"t":"SoftBreak"},{"t":"Str","c":"intermediate"},{"t":"Space"},{"t":"Str","c":"files"},{"t":"Space"},{"t":"Str","c":"which"},{"t":"Space"},{"t":"Str","c":"need"},{"t":"Space"},{"t":"Str","c":"not"},{"t":"Space"},{"t":"Str","c":"be"},{"t":"Space"},{"t":"Str","c":"saved."}]},{"t":"Para","c":[{"t":"Str","c":"GNU"},{"t":"Space"},{"t":"Str","c":"Make"},{"t":"Space"},{"t":"Str","c":"also"},{"t":"Space"},{"t":"Str","c":"has"},{"t":"Space"},{"t":"Str","c":"a"},{"t":"Space"},{"t":"Str","c":"few"},{"t":"Space"},{"t":"Str","c":"simple"},{"t":"Space"},{"t":"Str","c":"features"},{"t":"Space"},{"t":"Str","c":"that"},{"t":"Space"},{"t":"Str","c":"are"},{"t":"Space"},{"t":"Str","c":"very"},{"t":"Space"},{"t":"Str","c":"convenient."},{"t":"Space"},{"t":"Str","c":"For"},{"t":"SoftBreak"},{"t":"Str","c":"example,"},{"t":"Space"},{"t":"Str","c":"the"},{"t":"Space"},{"t":"Code","c":[["",[],[]],"-o "]},{"t":"Emph","c":[{"t":"Code","c":[["",[],[]],"file"]}]},{"t":"Space"},{"t":"Str","c":"option"},{"t":"Space"},{"t":"Str","c":"which"},{"t":"Space"},{"t":"Str","c":"says"},{"t":"Space"},{"t":"Str","c":"``pretend"},{"t":"Space"},{"t":"Str","c":"that"},{"t":"SoftBreak"},{"t":"Str","c":"source"},{"t":"Space"},{"t":"Str","c":"file"},{"t":"Space"},{"t":"Emph","c":[{"t":"Str","c":"file"}]},{"t":"Space"},{"t":"Str","c":"has"},{"t":"Space"},{"t":"Str","c":"not"},{"t":"Space"},{"t":"Str","c":"changed,"},{"t":"Space"},{"t":"Str","c":"even"},{"t":"Space"},{"t":"Str","c":"though"},{"t":"Space"},{"t":"Str","c":"it"},{"t":"Space"},{"t":"Str","c":"has"},{"t":"Space"},{"t":"Str","c":"changed.''"},{"t":"SoftBreak"},{"t":"Str","c":"This"},{"t":"Space"},{"t":"Str","c":"is"},{"t":"Space"},{"t":"Str","c":"extremely"},{"t":"Space"},{"t":"Str","c":"useful"},{"t":"Space"},{"t":"Str","c":"when"},{"t":"Space"},{"t":"Str","c":"you"},{"t":"Space"},{"t":"Str","c":"add"},{"t":"Space"},{"t":"Str","c":"a"},{"t":"Space"},{"t":"Str","c":"new"},{"t":"Space"},{"t":"Str","c":"macro"},{"t":"Space"},{"t":"Str","c":"to"},{"t":"Space"},{"t":"Str","c":"a"},{"t":"Space"},{"t":"Str","c":"header"},{"t":"Space"},{"t":"Str","c":"file."},{"t":"SoftBreak"},{"t":"Str","c":"Most"},{"t":"Space"},{"t":"Str","c":"versions"},{"t":"Space"},{"t":"Str","c":"of"},{"t":"Space"},{"t":"Str","c":"Make"},{"t":"Space"},{"t":"Str","c":"will"},{"t":"Space"},{"t":"Str","c":"assume"},{"t":"Space"},{"t":"Str","c":"they"},{"t":"Space"},{"t":"Str","c":"must"},{"t":"Space"},{"t":"Str","c":"therefore"},{"t":"Space"},{"t":"Str","c":"recompile"},{"t":"Space"},{"t":"Str","c":"all"},{"t":"Space"},{"t":"Str","c":"the"},{"t":"SoftBreak"},{"t":"Str","c":"source"},{"t":"Space"},{"t":"Str","c":"files"},{"t":"Space"},{"t":"Str","c":"that"},{"t":"Space"},{"t":"Str","c":"use"},{"t":"Space"},{"t":"Str","c":"the"},{"t":"Space"},{"t":"Str","c":"header"},{"t":"Space"},{"t":"Str","c":"file;"},{"t":"Space"},{"t":"Str","c":"but"},{"t":"Space"},{"t":"Str","c":"GNU"},{"t":"Space"},{"t":"Str","c":"Make"},{"t":"Space"},{"t":"Str","c":"gives"},{"t":"Space"},{"t":"Str","c":"you"},{"t":"Space"},{"t":"Str","c":"a"},{"t":"Space"},{"t":"Str","c":"way"},{"t":"Space"},{"t":"Str","c":"to"},{"t":"SoftBreak"},{"t":"Str","c":"avoid"},{"t":"Space"},{"t":"Str","c":"the"},{"t":"Space"},{"t":"Str","c":"recompilation,"},{"t":"Space"},{"t":"Str","c":"in"},{"t":"Space"},{"t":"Str","c":"the"},{"t":"Space"},{"t":"Str","c":"case"},{"t":"Space"},{"t":"Str","c":"where"},{"t":"Space"},{"t":"Str","c":"you"},{"t":"Space"},{"t":"Str","c":"know"},{"t":"Space"},{"t":"Str","c":"your"},{"t":"Space"},{"t":"Str","c":"change"},{"t":"Space"},{"t":"Str","c":"to"},{"t":"Space"},{"t":"Str","c":"the"},{"t":"SoftBreak"},{"t":"Str","c":"header"},{"t":"Space"},{"t":"Str","c":"file"},{"t":"Space"},{"t":"Str","c":"does"},{"t":"Space"},{"t":"Str","c":"not"},{"t":"Space"},{"t":"Str","c":"require"},{"t":"Space"},{"t":"Str","c":"it."}]},{"t":"Para","c":[{"t":"Str","c":"However,"},{"t":"Space"},{"t":"Str","c":"the"},{"t":"Space"},{"t":"Str","c":"most"},{"t":"Space"},{"t":"Str","c":"important"},{"t":"Space"},{"t":"Str","c":"difference"},{"t":"Space"},{"t":"Str","c":"between"},{"t":"Space"},{"t":"Str","c":"GNU"},{"t":"Space"},{"t":"Str","c":"Make"},{"t":"Space"},{"t":"Str","c":"and"},{"t":"Space"},{"t":"Str","c":"most"},{"t":"SoftBreak"},{"t":"Str","c":"versions"},{"t":"Space"},{"t":"Str","c":"of"},{"t":"Space"},{"t":"Str","c":"Make"},{"t":"Space"},{"t":"Str","c":"is"},{"t":"Space"},{"t":"Str","c":"that"},{"t":"Space"},{"t":"Str","c":"GNU"},{"t":"Space"},{"t":"Str","c":"Make"},{"t":"Space"},{"t":"Str","c":"is"},{"t":"Space"},{"t":"Str","c":"free"},{"t":"Space"},{"t":"Str","c":"software."}]},{"t":"Header","c":[4,["makefiles-and-conventions",[],[]],[{"t":"Str","c":"Makefiles"},{"t":"Space"},{"t":"Str","c":"And"},{"t":"Space"},{"t":"Str","c":"Conventions"}]]},{"t":"Para","c":[{"t":"Str","c":"We"},{"t":"Space"},{"t":"Str","c":"have"},{"t":"Space"},{"t":"Str","c":"developed"},{"t":"Space"},{"t":"Str","c":"conventions"},{"t":"Space"},{"t":"Str","c":"for"},{"t":"Space"},{"t":"Str","c":"how"},{"t":"Space"},{"t":"Str","c":"to"},{"t":"Space"},{"t":"Str","c":"write"},{"t":"Space"},{"t":"Str","c":"Makefiles,"},{"t":"Space"},{"t":"Str","c":"which"},{"t":"Space"},{"t":"Str","c":"all"},{"t":"SoftBreak"},{"t":"Str","c":"GNU"},{"t":"Space"},{"t":"Str","c":"packages"},{"t":"Space"},{"t":"Str","c":"ought"},{"t":"Space"},{"t":"Str","c":"to"},{"t":"Space"},{"t":"Str","c":"follow."},{"t":"Space"},{"t":"Str","c":"It"},{"t":"Space"},{"t":"Str","c":"is"},{"t":"Space"},{"t":"Str","c":"a"},{"t":"Space"},{"t":"Str","c":"good"},{"t":"Space"},{"t":"Str","c":"idea"},{"t":"Space"},{"t":"Str","c":"to"},{"t":"Space"},{"t":"Str","c":"follow"},{"t":"Space"},{"t":"Str","c":"these"},{"t":"SoftBreak"},{"t":"Str","c":"conventions"},{"t":"Space"},{"t":"Str","c":"in"},{"t":"Space"},{"t":"Str","c":"your"},{"t":"Space"},{"t":"Str","c":"program"},{"t":"Space"},{"t":"Str","c":"even"},{"t":"Space"},{"t":"Str","c":"if"},{"t":"Space"},{"t":"Str","c":"you"},{"t":"Space"},{"t":"Str","c":"don't"},{"t":"Space"},{"t":"Str","c":"intend"},{"t":"Space"},{"t":"Str","c":"it"},{"t":"Space"},{"t":"Str","c":"to"},{"t":"Space"},{"t":"Str","c":"be"},{"t":"Space"},{"t":"Str","c":"GNU"},{"t":"SoftBreak"},{"t":"Str","c":"software,"},{"t":"Space"},{"t":"Str","c":"so"},{"t":"Space"},{"t":"Str","c":"that"},{"t":"Space"},{"t":"Str","c":"users"},{"t":"Space"},{"t":"Str","c":"will"},{"t":"Space"},{"t":"Str","c":"be"},{"t":"Space"},{"t":"Str","c":"able"},{"t":"Space"},{"t":"Str","c":"to"},{"t":"Space"},{"t":"Str","c":"build"},{"t":"Space"},{"t":"Str","c":"your"},{"t":"Space"},{"t":"Str","c":"package"},{"t":"Space"},{"t":"Str","c":"just"},{"t":"SoftBreak"},{"t":"Str","c":"like"},{"t":"Space"},{"t":"Str","c":"many"},{"t":"Space"},{"t":"Str","c":"other"},{"t":"Space"},{"t":"Str","c":"packages,"},{"t":"Space"},{"t":"Str","c":"and"},{"t":"Space"},{"t":"Str","c":"will"},{"t":"Space"},{"t":"Str","c":"not"},{"t":"Space"},{"t":"Str","c":"need"},{"t":"Space"},{"t":"Str","c":"to"},{"t":"Space"},{"t":"Str","c":"learn"},{"t":"Space"},{"t":"Str","c":"anything"},{"t":"Space"},{"t":"Str","c":"special"},{"t":"SoftBreak"},{"t":"Str","c":"before"},{"t":"Space"},{"t":"Str","c":"doing"},{"t":"Space"},{"t":"Str","c":"so."}]},{"t":"Para","c":[{"t":"Str","c":"These"},{"t":"Space"},{"t":"Str","c":"conventions"},{"t":"Space"},{"t":"Str","c":"are"},{"t":"Space"},{"t":"Str","c":"found"},{"t":"Space"},{"t":"Str","c":"in"},{"t":"Space"},{"t":"Str","c":"the"},{"t":"Space"},{"t":"Str","c":"chapter"},{"t":"SoftBreak"},{"t":"Link","c":[["",[],[]],[{"t":"Str","c":"``Makefile"},{"t":"Space"},{"t":"Str","c":"conventions''"},{"t":"Space"},{"t":"Str","c":"(147"},{"t":"Space"},{"t":"Str","c":"k"},{"t":"SoftBreak"},{"t":"Str","c":"characters)"}],["/prep/standards/html_node/Makefile-Conventions.html#Makefile-Conventions",""]]},{"t":"Space"},{"t":"Str","c":"of"},{"t":"Space"},{"t":"Str","c":"the"},{"t":"Space"},{"t":"Link","c":[["",[],[]],[{"t":"Str","c":"GNU"},{"t":"Space"},{"t":"Str","c":"Coding"},{"t":"SoftBreak"},{"t":"Str","c":"Standards"},{"t":"Space"},{"t":"Str","c":"(147"},{"t":"Space"},{"t":"Str","c":"k"},{"t":"Space"},{"t":"Str","c":"characters)"}],["/prep/standards.html",""]]},{"t":"Str","c":"."}]},{"t":"Header","c":[3,["download",[],[]],[{"t":"Str","c":"Download"}]]},{"t":"Para","c":[{"t":"Str","c":"Make"},{"t":"SoftBreak"},{"t":"Str","c":"can"},{"t":"Space"},{"t":"Str","c":"be"},{"t":"Space"},{"t":"Str","c":"found"},{"t":"Space"},{"t":"Str","c":"on"},{"t":"Space"},{"t":"Str","c":"the"},{"t":"Space"},{"t":"Str","c":"main"},{"t":"Space"},{"t":"Str","c":"GNU"},{"t":"Space"},{"t":"Str","c":"ftp"},{"t":"Space"},{"t":"Str","c":"server"},{"t":"SoftBreak"},{"t":"Str","c":"("},{"t":"Link","c":[["",[],[]],[{"t":"Str","c":"download"},{"t":"Space"},{"t":"Span","c":[["",["no-display"],[]],[{"t":"Str","c":"Make"},{"t":"Space"}]]},{"t":"Str","c":"via"},{"t":"Space"},{"t":"Str","c":"HTTPS"}],["https://ftp.gnu.org/gnu/make/",""]]},{"t":"Str","c":", "},{"t":"SoftBreak"},{"t":"Link","c":[["",[],[]],[{"t":"Span","c":[["",["no-display"],[]],[{"t":"Str","c":"download"},{"t":"Space"},{"t":"Str","c":"Make"},{"t":"Space"},{"t":"Str","c":"via"},{"t":"Space"}]]},{"t":"Str","c":"HTTP"}],["http://ftp.gnu.org/gnu/make/",""]]},{"t":"Space"},{"t":"Str","c":"or"},{"t":"SoftBreak"},{"t":"Link","c":[["",[],[]],[{"t":"Span","c":[["",["no-display"],[]],[{"t":"Str","c":"download"},{"t":"Space"},{"t":"Str","c":"Make"},{"t":"Space"},{"t":"Str","c":"via"},{"t":"Space"}]]},{"t":"Str","c":"FTP"}],["ftp://ftp.gnu.org/gnu/make/",""]]},{"t":"Str","c":"),"},{"t":"Space"},{"t":"Str","c":"and"},{"t":"Space"},{"t":"Str","c":"its"},{"t":"SoftBreak"},{"t":"Link","c":[["",[],[]],[{"t":"Str","c":"mirrors"}],["/prep/ftp.html",""]]},{"t":"Str","c":";"},{"t":"Space"},{"t":"Str","c":"please"},{"t":"SoftBreak"},{"t":"Link","c":[["",[],[]],[{"t":"Str","c":"use"},{"t":"Space"},{"t":"Str","c":"a"},{"t":"Space"},{"t":"Str","c":"mirror"}],["https://ftpmirror.gnu.org/make/",""]]},{"t":"SoftBreak"},{"t":"Str","c":"if"},{"t":"Space"},{"t":"Str","c":"possible."}]},{"t":"Header","c":[3,["documentation",[],[]],[{"t":"Str","c":"Documentation"}]]},{"t":"Para","c":[{"t":"Link","c":[["",[],[]],[{"t":"Str","c":"Documentation"},{"t":"Space"},{"t":"Str","c":"for"},{"t":"SoftBreak"},{"t":"Str","c":"Make"}],["manual/",""]]},{"t":"SoftBreak"},{"t":"Str","c":"is"},{"t":"Space"},{"t":"Str","c":"online,"},{"t":"Space"},{"t":"Str","c":"as"},{"t":"Space"},{"t":"Str","c":"is"},{"t":"Space"},{"t":"Link","c":[["",[],[]],[{"t":"Str","c":"documentation"},{"t":"Space"},{"t":"Str","c":"for"},{"t":"Space"},{"t":"Str","c":"most"},{"t":"SoftBreak"},{"t":"Str","c":"GNU"},{"t":"Space"},{"t":"Str","c":"software"}],["/manual/manual.html",""]]},{"t":"Str","c":"."},{"t":"Space"},{"t":"Str","c":"It"},{"t":"Space"},{"t":"Str","c":"can"},{"t":"Space"},{"t":"Str","c":"also"},{"t":"Space"},{"t":"Str","c":"be"},{"t":"Space"},{"t":"Str","c":"accessed"},{"t":"Space"},{"t":"Str","c":"by"},{"t":"Space"},{"t":"Str","c":"running"},{"t":"SoftBreak"},{"t":"Span","c":[["",["kbd"],[]],[{"t":"Str","c":"info make"}]]},{"t":"Space"},{"t":"Str","c":"or"},{"t":"SoftBreak"},{"t":"Span","c":[["",["kbd"],[]],[{"t":"Str","c":"man make"}]]},{"t":"Str","c":","},{"t":"Space"},{"t":"Str","c":"or"},{"t":"Space"},{"t":"Str","c":"by"},{"t":"Space"},{"t":"Str","c":"looking"},{"t":"Space"},{"t":"Str","c":"at"},{"t":"SoftBreak"},{"t":"Code","c":[["",[],[]],"/usr/share/doc/make/"]},{"t":"Str","c":","},{"t":"SoftBreak"},{"t":"Str","c":"or"},{"t":"Space"},{"t":"Str","c":"similar"},{"t":"Space"},{"t":"Str","c":"directories"},{"t":"Space"},{"t":"Str","c":"on"},{"t":"Space"},{"t":"Str","c":"your"},{"t":"Space"},{"t":"Str","c":"system."},{"t":"Space"},{"t":"Str","c":"A"},{"t":"Space"},{"t":"Str","c":"brief"},{"t":"Space"},{"t":"Str","c":"summary"},{"t":"Space"},{"t":"Str","c":"is"},{"t":"Space"},{"t":"Str","c":"available"},{"t":"Space"},{"t":"Str","c":"by"},{"t":"SoftBreak"},{"t":"Str","c":"running"},{"t":"Space"},{"t":"Span","c":[["",["kbd"],[]],[{"t":"Str","c":"make --help"}]]},{"t":"Str","c":"."}]},{"t":"Header","c":[3,["mail",[],[]],[{"t":"Str","c":"Mailing"},{"t":"Space"},{"t":"Str","c":"lists"}]]},{"t":"Para","c":[{"t":"Str","c":"Make"},{"t":"SoftBreak"},{"t":"Str","c":"has"},{"t":"Space"},{"t":"Str","c":"the"},{"t":"Space"},{"t":"Str","c":"following"},{"t":"Space"},{"t":"Str","c":"mailing"},{"t":"Space"},{"t":"Str","c":"lists:"}]},{"t":"BulletList","c":[[{"t":"Plain","c":[{"t":"Link","c":[["",[],[]],[{"t":"Str","c":"bug-make"}],["https://lists.gnu.org/mailman/listinfo/bug-make",""]]},{"t":"SoftBreak"},{"t":"Str","c":"for"},{"t":"Space"},{"t":"Str","c":"discussing"},{"t":"Space"},{"t":"Str","c":"most"},{"t":"Space"},{"t":"Str","c":"aspects"},{"t":"Space"},{"t":"Str","c":"of"},{"t":"SoftBreak"},{"t":"Str","c":"Make,"},{"t":"SoftBreak"},{"t":"Str","c":"including"},{"t":"Space"},{"t":"Str","c":"development"},{"t":"Space"},{"t":"Str","c":"and"},{"t":"Space"},{"t":"Str","c":"enhancement"},{"t":"Space"},{"t":"Str","c":"requests,"},{"t":"Space"},{"t":"Str","c":"as"},{"t":"Space"},{"t":"Str","c":"well"},{"t":"Space"},{"t":"Str","c":"as"},{"t":"Space"},{"t":"Str","c":"bug"},{"t":"Space"},{"t":"Str","c":"reports."}]}],[{"t":"Plain","c":[{"t":"Link","c":[["",[],[]],[{"t":"Str","c":"help-make"}],["https://lists.gnu.org/mailman/listinfo/help-make",""]]},{"t":"SoftBreak"},{"t":"Str","c":"for"},{"t":"Space"},{"t":"Str","c":"general"},{"t":"Space"},{"t":"Str","c":"user"},{"t":"Space"},{"t":"Str","c":"help"},{"t":"Space"},{"t":"Str","c":"and"},{"t":"Space"},{"t":"Str","c":"discussion."}]}]]},{"t":"Para","c":[{"t":"Str","c":"Announcements"},{"t":"Space"},{"t":"Str","c":"about"},{"t":"SoftBreak"},{"t":"Str","c":"Make"},{"t":"SoftBreak"},{"t":"Str","c":"and"},{"t":"Space"},{"t":"Str","c":"most"},{"t":"Space"},{"t":"Str","c":"other"},{"t":"Space"},{"t":"Str","c":"GNU"},{"t":"Space"},{"t":"Str","c":"software"},{"t":"Space"},{"t":"Str","c":"are"},{"t":"Space"},{"t":"Str","c":"made"},{"t":"Space"},{"t":"Str","c":"on"},{"t":"Space"},{"t":"Str","c":"the"},{"t":"SoftBreak"},{"t":"Link","c":[["",[],[]],[{"t":"Str","c":"info-gnu"}],["https://lists.gnu.org/mailman/listinfo/info-gnu",""]]},{"t":"SoftBreak"},{"t":"Str","c":"mailing"},{"t":"Space"},{"t":"Str","c":"list"},{"t":"SoftBreak"},{"t":"Str","c":"("},{"t":"Link","c":[["",[],[]],[{"t":"Str","c":"archives"}],["https://lists.gnu.org/archive/html/info-gnu/",""]]},{"t":"Str","c":")."}]},{"t":"Para","c":[{"t":"Str","c":"Security"},{"t":"Space"},{"t":"Str","c":"reports"},{"t":"Space"},{"t":"Str","c":"that"},{"t":"Space"},{"t":"Str","c":"should"},{"t":"Space"},{"t":"Str","c":"not"},{"t":"Space"},{"t":"Str","c":"be"},{"t":"Space"},{"t":"Str","c":"made"},{"t":"Space"},{"t":"Str","c":"immediately"},{"t":"Space"},{"t":"Str","c":"public"},{"t":"Space"},{"t":"Str","c":"can"},{"t":"Space"},{"t":"Str","c":"be"},{"t":"SoftBreak"},{"t":"Str","c":"sent"},{"t":"Space"},{"t":"Str","c":"directly"},{"t":"Space"},{"t":"Str","c":"to"},{"t":"Space"},{"t":"Str","c":"the"},{"t":"Space"},{"t":"Str","c":"maintainer."},{"t":"Space"},{"t":"Str","c":"If"},{"t":"Space"},{"t":"Str","c":"there"},{"t":"Space"},{"t":"Str","c":"is"},{"t":"Space"},{"t":"Str","c":"no"},{"t":"Space"},{"t":"Str","c":"response"},{"t":"Space"},{"t":"Str","c":"to"},{"t":"Space"},{"t":"Str","c":"an"},{"t":"Space"},{"t":"Str","c":"urgent"},{"t":"SoftBreak"},{"t":"Str","c":"issue,"},{"t":"Space"},{"t":"Str","c":"you"},{"t":"Space"},{"t":"Str","c":"can"},{"t":"Space"},{"t":"Str","c":"escalate"},{"t":"Space"},{"t":"Str","c":"to"},{"t":"Space"},{"t":"Str","c":"the"},{"t":"Space"},{"t":"Str","c":"general"},{"t":"SoftBreak"},{"t":"Link","c":[["",[],[]],[{"t":"Str","c":"security"}],["https://lists.gnu.org/mailman/listinfo/security",""]]},{"t":"SoftBreak"},{"t":"Str","c":"mailing"},{"t":"Space"},{"t":"Str","c":"list"},{"t":"Space"},{"t":"Str","c":"for"},{"t":"Space"},{"t":"Str","c":"advice."}]},{"t":"Header","c":[3,["contribute",[],[]],[{"t":"Str","c":"Getting"},{"t":"Space"},{"t":"Str","c":"involved"}]]},{"t":"Para","c":[{"t":"Str","c":"Development"},{"t":"Space"},{"t":"Str","c":"of"},{"t":"SoftBreak"},{"t":"Str","c":"Make,"},{"t":"SoftBreak"},{"t":"Str","c":"and"},{"t":"Space"},{"t":"Str","c":"GNU"},{"t":"Space"},{"t":"Str","c":"in"},{"t":"Space"},{"t":"Str","c":"general,"},{"t":"Space"},{"t":"Str","c":"is"},{"t":"Space"},{"t":"Str","c":"a"},{"t":"Space"},{"t":"Str","c":"volunteer"},{"t":"Space"},{"t":"Str","c":"effort,"},{"t":"Space"},{"t":"Str","c":"and"},{"t":"Space"},{"t":"Str","c":"you"},{"t":"Space"},{"t":"Str","c":"can"},{"t":"Space"},{"t":"Str","c":"contribute."},{"t":"Space"},{"t":"Str","c":"For"},{"t":"SoftBreak"},{"t":"Str","c":"information,"},{"t":"Space"},{"t":"Str","c":"please"},{"t":"Space"},{"t":"Str","c":"read"},{"t":"Space"},{"t":"Link","c":[["",[],[]],[{"t":"Str","c":"How"},{"t":"Space"},{"t":"Str","c":"to"},{"t":"Space"},{"t":"Str","c":"help"},{"t":"Space"},{"t":"Str","c":"GNU"}],["/help/",""]]},{"t":"Str","c":"."},{"t":"Space"},{"t":"Str","c":"If"},{"t":"Space"},{"t":"Str","c":"you'd"},{"t":"SoftBreak"},{"t":"Str","c":"like"},{"t":"Space"},{"t":"Str","c":"to"},{"t":"Space"},{"t":"Str","c":"get"},{"t":"Space"},{"t":"Str","c":"involved,"},{"t":"Space"},{"t":"Str","c":"it's"},{"t":"Space"},{"t":"Str","c":"a"},{"t":"Space"},{"t":"Str","c":"good"},{"t":"Space"},{"t":"Str","c":"idea"},{"t":"Space"},{"t":"Str","c":"to"},{"t":"Space"},{"t":"Str","c":"join"},{"t":"Space"},{"t":"Str","c":"the"},{"t":"Space"},{"t":"Str","c":"discussion"},{"t":"Space"},{"t":"Str","c":"mailing"},{"t":"SoftBreak"},{"t":"Str","c":"list"},{"t":"Space"},{"t":"Str","c":"(see"},{"t":"Space"},{"t":"Str","c":"above)."}]},{"t":"DefinitionList","c":[[[{"t":"Str","c":"Development"},{"t":"Space"},{"t":"Str","c":"tools"}],[[{"t":"Plain","c":[{"t":"Str","c":"For"},{"t":"Space"},{"t":"Str","c":"development"},{"t":"Space"},{"t":"Str","c":"sources,"},{"t":"Space"},{"t":"Str","c":"issue"},{"t":"Space"},{"t":"Str","c":"trackers,"},{"t":"Space"},{"t":"Str","c":"and"},{"t":"Space"},{"t":"Str","c":"other"},{"t":"SoftBreak"},{"t":"Str","c":"information,"},{"t":"Space"},{"t":"Str","c":"please"},{"t":"Space"},{"t":"Str","c":"see"},{"t":"Space"},{"t":"Str","c":"the"},{"t":"SoftBreak"},{"t":"Link","c":[["",[],[]],[{"t":"Str","c":"Make"},{"t":"SoftBreak"},{"t":"Str","c":"project"},{"t":"Space"},{"t":"Str","c":"page"}],["https://savannah.gnu.org/projects/make/",""]]},{"t":"SoftBreak"},{"t":"Str","c":"at"},{"t":"Space"},{"t":"Link","c":[["",[],[]],[{"t":"Str","c":"savannah.gnu.org"}],["https://savannah.gnu.org",""]]},{"t":"Str","c":"."}]}]]],[[{"t":"Str","c":"Testing"}],[[{"t":"Plain","c":[{"t":"Str","c":"Trying"},{"t":"Space"},{"t":"Str","c":"the"},{"t":"Space"},{"t":"Str","c":"latest"},{"t":"Space"},{"t":"Str","c":"test"},{"t":"Space"},{"t":"Str","c":"release"},{"t":"Space"},{"t":"Str","c":"(when"},{"t":"Space"},{"t":"Str","c":"available)"},{"t":"Space"},{"t":"Str","c":"is"},{"t":"Space"},{"t":"Str","c":"always"},{"t":"SoftBreak"},{"t":"Str","c":"appreciated."},{"t":"Space"},{"t":"Str","c":"Test"},{"t":"Space"},{"t":"Str","c":"releases"},{"t":"Space"},{"t":"Str","c":"can"},{"t":"Space"},{"t":"Str","c":"be"},{"t":"Space"},{"t":"Str","c":"found"},{"t":"Space"},{"t":"Str","c":"on"},{"t":"Space"},{"t":"Str","c":"the"},{"t":"Space"},{"t":"Str","c":"GNU"},{"t":"Space"},{"t":"Str","c":"“alpha”"},{"t":"SoftBreak"},{"t":"Str","c":"server"},{"t":"SoftBreak"},{"t":"Str","c":"("},{"t":"Link","c":[["",[],[]],[{"t":"Str","c":"HTTPS"}],["https://alpha.gnu.org/gnu/make/",""]]},{"t":"Str","c":", "},{"t":"SoftBreak"},{"t":"Link","c":[["",[],[]],[{"t":"Str","c":"HTTP"}],["http://alpha.gnu.org/gnu/make/",""]]},{"t":"Str","c":", "},{"t":"SoftBreak"},{"t":"Link","c":[["",[],[]],[{"t":"Str","c":"FTP"}],["ftp://alpha.gnu.org/gnu/make/",""]]},{"t":"Str","c":")"},{"t":"Space"},{"t":"Str","c":"and"},{"t":"Space"},{"t":"Str","c":"its"},{"t":"SoftBreak"},{"t":"Link","c":[["",[],[]],[{"t":"Str","c":"mirrors"}],["/prep/ftp.html",""]]},{"t":"Str","c":"."}]}]]],[[{"t":"Str","c":"Translating"}],[[{"t":"Plain","c":[{"t":"Str","c":"To"},{"t":"Space"},{"t":"Str","c":"translate"},{"t":"Space"},{"t":"Str","c":"the"},{"t":"Space"},{"t":"Str","c":"program"},{"t":"Space"},{"t":"Str","c":"messages"},{"t":"Space"},{"t":"Str","c":"into"},{"t":"Space"},{"t":"Str","c":"other"},{"t":"Space"},{"t":"Str","c":"languages,"},{"t":"Space"},{"t":"Str","c":"please"},{"t":"Space"},{"t":"Str","c":"refer"},{"t":"SoftBreak"},{"t":"Str","c":"to"},{"t":"Space"},{"t":"Str","c":"the"},{"t":"SoftBreak"},{"t":"Link","c":[["",[],[]],[{"t":"Str","c":"Translation"},{"t":"Space"},{"t":"Str","c":"Project"},{"t":"Space"},{"t":"Str","c":"page"},{"t":"Space"},{"t":"Str","c":"for"},{"t":"SoftBreak"},{"t":"Str","c":"Make"}],["https://translationproject.org/domain/make.html",""]]},{"t":"Str","c":"."},{"t":"SoftBreak"},{"t":"Str","c":"New"},{"t":"Space"},{"t":"Str","c":"translations"},{"t":"Space"},{"t":"Str","c":"or"},{"t":"Space"},{"t":"Str","c":"updates"},{"t":"Space"},{"t":"Str","c":"to"},{"t":"Space"},{"t":"Str","c":"the"},{"t":"Space"},{"t":"Str","c":"existing"},{"t":"Space"},{"t":"Str","c":"strings"},{"t":"Space"},{"t":"Str","c":"will"},{"t":"Space"},{"t":"Str","c":"not"},{"t":"Space"},{"t":"Str","c":"be"},{"t":"SoftBreak"},{"t":"Str","c":"incorporated"},{"t":"Space"},{"t":"Str","c":"into"},{"t":"SoftBreak"},{"t":"Str","c":"Make"},{"t":"SoftBreak"},{"t":"Str","c":"if"},{"t":"Space"},{"t":"Str","c":"they"},{"t":"Space"},{"t":"Str","c":"are"},{"t":"Space"},{"t":"Str","c":"sent"},{"t":"Space"},{"t":"Str","c":"elsewhere."},{"t":"Space"},{"t":"Str","c":"For"},{"t":"Space"},{"t":"Str","c":"more"},{"t":"Space"},{"t":"Str","c":"information,"},{"t":"Space"},{"t":"Str","c":"see"},{"t":"Space"},{"t":"Str","c":"the"},{"t":"Space"},{"t":"Link","c":[["",[],[]],[{"t":"Str","c":"Translation"},{"t":"SoftBreak"},{"t":"Str","c":"Project"},{"t":"Space"},{"t":"Str","c":"home"},{"t":"Space"},{"t":"Str","c":"page"}],["https://translationproject.org/html/welcome.html",""]]},{"t":"Str","c":"."}]}]]],[[{"t":"Str","c":"Maintainer"}],[[{"t":"Plain","c":[{"t":"Str","c":"Make"},{"t":"SoftBreak"},{"t":"Str","c":"is"},{"t":"Space"},{"t":"Str","c":"currently"},{"t":"Space"},{"t":"Str","c":"maintained"},{"t":"Space"},{"t":"Str","c":"by"},{"t":"SoftBreak"},{"t":"Str","c":"Paul"},{"t":"Space"},{"t":"Str","c":"Smith."},{"t":"SoftBreak"},{"t":"Str","c":"Please"},{"t":"Space"},{"t":"Str","c":"use"},{"t":"Space"},{"t":"Str","c":"the"},{"t":"Space"},{"t":"Str","c":"mailing"},{"t":"Space"},{"t":"Str","c":"lists"},{"t":"Space"},{"t":"Str","c":"for"},{"t":"Space"},{"t":"Str","c":"contact."}]}]]]]},{"t":"Header","c":[3,["license",[],[]],[{"t":"Str","c":"Licensing"}]]},{"t":"Para","c":[{"t":"Str","c":"Make"},{"t":"SoftBreak"},{"t":"Str","c":"is"},{"t":"Space"},{"t":"Str","c":"free"},{"t":"Space"},{"t":"Str","c":"software;"},{"t":"Space"},{"t":"Str","c":"you"},{"t":"Space"},{"t":"Str","c":"can"},{"t":"Space"},{"t":"Str","c":"redistribute"},{"t":"Space"},{"t":"Str","c":"it"},{"t":"Space"},{"t":"Str","c":"and/or"},{"t":"Space"},{"t":"Str","c":"modify"},{"t":"Space"},{"t":"Str","c":"it"},{"t":"Space"},{"t":"Str","c":"under"},{"t":"Space"},{"t":"Str","c":"the"},{"t":"SoftBreak"},{"t":"Str","c":"terms"},{"t":"Space"},{"t":"Str","c":"of"},{"t":"Space"},{"t":"Str","c":"the"},{"t":"Space"},{"t":"Link","c":[["",[],[["rel","license"]]],[{"t":"Str","c":"GNU"},{"t":"Space"},{"t":"Str","c":"General"},{"t":"SoftBreak"},{"t":"Str","c":"Public"},{"t":"Space"},{"t":"Str","c":"License"}],["/licenses/gpl.html",""]]},{"t":"Space"},{"t":"Str","c":"as"},{"t":"Space"},{"t":"Str","c":"published"},{"t":"Space"},{"t":"Str","c":"by"},{"t":"Space"},{"t":"Str","c":"the"},{"t":"Space"},{"t":"Str","c":"Free"},{"t":"Space"},{"t":"Str","c":"Software"},{"t":"Space"},{"t":"Str","c":"Foundation;"},{"t":"Space"},{"t":"Str","c":"either"},{"t":"SoftBreak"},{"t":"Str","c":"version 3"},{"t":"Space"},{"t":"Str","c":"of"},{"t":"Space"},{"t":"Str","c":"the"},{"t":"Space"},{"t":"Str","c":"License,"},{"t":"Space"},{"t":"Str","c":"or"},{"t":"Space"},{"t":"Str","c":"(at"},{"t":"Space"},{"t":"Str","c":"your"},{"t":"Space"},{"t":"Str","c":"option)"},{"t":"Space"},{"t":"Str","c":"any"},{"t":"Space"},{"t":"Str","c":"later"},{"t":"Space"},{"t":"Str","c":"version."}]}]]},{"t":"Div","c":[["",[],[["style","clear:both"]]],[]]},{"t":"Div","c":[["mission-statement",[],[["role","complementary"]]],[{"t":"Div","c":[["",["backtotop"],[]],[{"t":"HorizontalRule"},{"t":"Plain","c":[{"t":"Link","c":[["",[],[]],[{"t":"Span","c":[["",[],[]],[{"t":"Str","c":"BACK"},{"t":"Space"},{"t":"Str","c":"TO"},{"t":"Space"},{"t":"Str","c":"TOP"},{"t":"Space"}]]},{"t":"Str","c":"▲"}],["#header",""]]}]}]]},{"t":"Div","c":[["",[],[["style","clear: both"]]],[]]},{"t":"BlockQuote","c":[{"t":"Para","c":[{"t":"Link","c":[["",[],[]],[{"t":"Image","c":[["fsfbanner",[],[["width","75"],["height","25"]]],[{"t":"Str","c":" [FSF"},{"t":"Space"},{"t":"Str","c":"logo] "}],["/graphics/fsf-logo-notext-small.png",""]]}],["//www.fsf.org",""]]},{"t":"SoftBreak"},{"t":"Strong","c":[{"t":"Str","c":"“The"},{"t":"Space"},{"t":"Str","c":"Free"},{"t":"Space"},{"t":"Str","c":"Software"},{"t":"Space"},{"t":"Str","c":"Foundation"},{"t":"Space"},{"t":"Str","c":"(FSF)"},{"t":"Space"},{"t":"Str","c":"is"},{"t":"Space"},{"t":"Str","c":"a"},{"t":"Space"},{"t":"Str","c":"nonprofit"},{"t":"Space"},{"t":"Str","c":"with"},{"t":"Space"},{"t":"Str","c":"a"},{"t":"Space"},{"t":"Str","c":"worldwide"},{"t":"SoftBreak"},{"t":"Str","c":"mission"},{"t":"Space"},{"t":"Str","c":"to"},{"t":"Space"},{"t":"Str","c":"promote"},{"t":"Space"},{"t":"Str","c":"computer"},{"t":"Space"},{"t":"Str","c":"user"},{"t":"Space"},{"t":"Str","c":"freedom."},{"t":"Space"},{"t":"Str","c":"We"},{"t":"Space"},{"t":"Str","c":"defend"},{"t":"Space"},{"t":"Str","c":"the"},{"t":"Space"},{"t":"Str","c":"rights"},{"t":"Space"},{"t":"Str","c":"of"},{"t":"Space"},{"t":"Str","c":"all"},{"t":"SoftBreak"},{"t":"Str","c":"software"},{"t":"Space"},{"t":"Str","c":"users.”"}]}]}]},{"t":"Div","c":[["support-the-fsf",["button"],[]],[{"t":"Plain","c":[{"t":"Link","c":[["",["join"],[]],[{"t":"Str","c":"JOIN"}],["//www.fsf.org/associate/support_freedom?referrer=4052",""]]},{"t":"SoftBreak"},{"t":"Link","c":[["",["donate"],[]],[{"t":"Str","c":"DONATE"}],["//donate.fsf.org/",""]]},{"t":"SoftBreak"},{"t":"Link","c":[["",["shop"],[]],[{"t":"Str","c":"SHOP"}],["//shop.fsf.org/",""]]}]}]]}]]},{"t":"Div","c":[["footer",[],[["role","contentinfo"]]],[{"t":"Div","c":[["",["unprintable"],[]],[{"t":"Para","c":[{"t":"Str","c":"Please"},{"t":"Space"},{"t":"Str","c":"send"},{"t":"Space"},{"t":"Str","c":"general"},{"t":"Space"},{"t":"Str","c":"FSF"},{"t":"Space"},{"t":"Str","c":"&"},{"t":"Space"},{"t":"Str","c":"GNU"},{"t":"Space"},{"t":"Str","c":"inquiries"},{"t":"Space"},{"t":"Str","c":"to"},{"t":"SoftBreak"},{"t":"Link","c":[["",[],[]],[{"t":"Str","c":"<gnu@gnu.org>"}],["mailto:gnu@gnu.org",""]]},{"t":"Str","c":"."},{"t":"SoftBreak"},{"t":"Str","c":"There"},{"t":"Space"},{"t":"Str","c":"are"},{"t":"Space"},{"t":"Str","c":"also"},{"t":"Space"},{"t":"Link","c":[["",[],[]],[{"t":"Str","c":"other"},{"t":"Space"},{"t":"Str","c":"ways"},{"t":"Space"},{"t":"Str","c":"to"},{"t":"Space"},{"t":"Str","c":"contact"}],["/contact/",""]]},{"t":"SoftBreak"},{"t":"Str","c":"the"},{"t":"Space"},{"t":"Str","c":"FSF."},{"t":"Space"},{"t":"Str","c":"Broken"},{"t":"Space"},{"t":"Str","c":"links"},{"t":"Space"},{"t":"Str","c":"and"},{"t":"Space"},{"t":"Str","c":"other"},{"t":"Space"},{"t":"Str","c":"corrections"},{"t":"Space"},{"t":"Str","c":"or"},{"t":"Space"},{"t":"Str","c":"suggestions"},{"t":"Space"},{"t":"Str","c":"can"},{"t":"Space"},{"t":"Str","c":"be"},{"t":"Space"},{"t":"Str","c":"sent"},{"t":"SoftBreak"},{"t":"Str","c":"to"},{"t":"Space"},{"t":"Link","c":[["",[],[]],[{"t":"Str","c":"<bug-make@gnu.org>"}],["mailto:bug-make@gnu.org",""]]},{"t":"Str","c":"."}]},{"t":"Para","c":[{"t":"Str","c":"Please"},{"t":"Space"},{"t":"Str","c":"see"},{"t":"Space"},{"t":"Str","c":"the"},{"t":"Space"},{"t":"Link","c":[["",[],[]],[{"t":"Str","c":"Translations"},{"t":"SoftBreak"},{"t":"Str","c":"README"}],["/server/standards/README.translations.html",""]]},{"t":"Space"},{"t":"Str","c":"for"},{"t":"Space"},{"t":"Str","c":"information"},{"t":"Space"},{"t":"Str","c":"on"},{"t":"Space"},{"t":"Str","c":"coordinating"},{"t":"Space"},{"t":"Str","c":"and"},{"t":"Space"},{"t":"Str","c":"contributing"},{"t":"Space"},{"t":"Str","c":"translations"},{"t":"SoftBreak"},{"t":"Str","c":"of"},{"t":"Space"},{"t":"Str","c":"this"},{"t":"Space"},{"t":"Str","c":"article."}]}]]},{"t":"Para","c":[{"t":"Str","c":"Copyright"},{"t":"Space"},{"t":"Str","c":"©"},{"t":"Space"},{"t":"Str","c":"2023"},{"t":"Space"},{"t":"Str","c":"Free"},{"t":"Space"},{"t":"Str","c":"Software"},{"t":"Space"},{"t":"Str","c":"Foundation,"},{"t":"Space"},{"t":"Str","c":"Inc."}]},{"t":"Para","c":[{"t":"Str","c":"This"},{"t":"Space"},{"t":"Str","c":"page"},{"t":"Space"},{"t":"Str","c":"is"},{"t":"Space"},{"t":"Str","c":"licensed"},{"t":"Space"},{"t":"Str","c":"under"},{"t":"Space"},{"t":"Str","c":"a"},{"t":"Space"},{"t":"Link","c":[["",[],[["rel","license"]]],[{"t":"Str","c":"Creative"},{"t":"SoftBreak"},{"t":"Str","c":"Commons"},{"t":"Space"},{"t":"Str","c":"Attribution-NoDerivatives"},{"t":"Space"},{"t":"Str","c":"4.0"},{"t":"Space"},{"t":"Str","c":"International"},{"t":"Space"},{"t":"Str","c":"License"}],["http://creativecommons.org/licenses/by-nd/4.0/",""]]},{"t":"Str","c":"."}]},{"t":"Div","c":[["bottom-notes",["unprintable"],[]],[{"t":"Para","c":[{"t":"Link","c":[["",[],[]],[{"t":"Str","c":"Copyright"},{"t":"Space"},{"t":"Str","c":"Infringement"},{"t":"Space"},{"t":"Str","c":"Notification"}],["//www.fsf.org/about/dmca-notice",""]]}]},{"t":"Div","c":[["generic",[],[]],[]]}]]},{"t":"Para","c":[{"t":"Str","c":"Updated:"},{"t":"SoftBreak"},{"t":"Str","c":"$Date:"},{"t":"Space"},{"t":"Str","c":"2023/02/26"},{"t":"Space"},{"t":"Str","c":"19:56:54"},{"t":"Space"},{"t":"Str","c":"$"}]}]]}]]}]}
